pytest_markdir/plugin.py
pytest_markdir-0.1.0.dist-info/licenses/LICENSE
pytest_markdir-0.1.0.dist-info/METADATA
pytest_markdir-0.1.0.dist-info/WHEEL
pytest_markdir-0.1.0.dist-info/entry_points.txt
pytest_markdir-0.1.0.dist-info/top_level.txt
pytest_markdir-0.1.0.dist-info/RECORD
