Metadata-Version: 2.4
Name: pytest-markdir
Version: 0.1.0
License-File: LICENSE
Requires-Dist: pytest<10,>=8.0
Dynamic: license-file
